snake/__init__.py
snake/events.py
snake/snäke.py
pygame.snake-0.0.1a0.dist-info/LICENSE
pygame.snake-0.0.1a0.dist-info/METADATA
pygame.snake-0.0.1a0.dist-info/WHEEL
pygame.snake-0.0.1a0.dist-info/top_level.txt
pygame.snake-0.0.1a0.dist-info/RECORD
