Metadata-Version: 2.1
Name: pygame.snake
Version: 0.0.1a0
Summary: The super-simple pygame framework.
Home-page: https://github.com/Bottersnike/snake
Author: Bottersnike
Author-email: bottersnike237@gmail.com
License: MIT
Project-URL: Wiki, https://github.com/Bottersnike/Snake/wiki
Project-URL: Source, https://github.com/Bottersnike/Snake
Keywords: engine python pygame
Platform: UNKNOWN
Classifier: Development Status :: 3 - Alpha
Classifier: Environment :: Other Environment
Classifier: Intended Audience :: Developers
Classifier: License :: OSI Approved :: MIT License
Classifier: Programming Language :: Python :: 3
Classifier: Topic :: Games/Entertainment
